vzenith_camera/__init__.py
vzenith_camera/camera.py
vzenith_camera/emitter.py
vzenith_camera/socket.py
vzenith_camera/types.py
vzenith_camera-0.5.0.dist-info/LICENSE
vzenith_camera-0.5.0.dist-info/METADATA
vzenith_camera-0.5.0.dist-info/WHEEL
vzenith_camera-0.5.0.dist-info/RECORD
