Metadata-Version: 2.1
Name: vzenith-camera
Version: 0.5.0
Summary: A Python library for VisionZenith Smart Camera SDK in TCP protocol.
Home-page: https://github.com/garrett-he/vzenith-camera
License: BSD-3-Clause
Keywords: smart-camera,license-plate-recognition,intelligent-video-system,vision-zenith
Author: Garrett HE
Author-email: garrett.he@hotmail.com
Requires-Python: >=3.8,<3.12
Classifier: Development Status :: 3 - Alpha
Classifier: Intended Audience :: Developers
Classifier: License :: OSI Approved :: BSD License
Classifier: Operating System :: OS Independent
Classifier: Programming Language :: Python :: 3
Classifier: Programming Language :: Python :: 3.8
Classifier: Programming Language :: Python :: 3.9
Classifier: Programming Language :: Python :: 3.10
Classifier: Programming Language :: Python :: 3.11
Classifier: Topic :: Software Development :: Libraries :: Python Modules
Classifier: Topic :: System :: Monitoring
Project-URL: Repository, https://github.com/garrett-he/vzenith-camera.git
